LICENSE
README.md
setup.py
corpwechatbot/__about__.py
corpwechatbot/__init__.py
corpwechatbot/_sender.py
corpwechatbot/app.py
corpwechatbot/chatbot.py
corpwechatbot/command.py
corpwechatbot/config.py
corpwechatbot/error.py
corpwechatbot/util.py
corpwechatbot.egg-info/PKG-INFO
corpwechatbot.egg-info/SOURCES.txt
corpwechatbot.egg-info/dependency_links.txt
corpwechatbot.egg-info/entry_points.txt
corpwechatbot.egg-info/requires.txt
corpwechatbot.egg-info/top_level.txt