Metadata-Version: 2.1
Name: corpwechatbot
Version: 0.6.4
Summary: corpwechatbot
Home-page: https://github.com/GentleCP/corpwechatbot
Author: GentleCP
Author-email: me@gentlecp.com
License: GPL v3
Platform: any
Classifier: Programming Language :: Python :: 3
Classifier: License :: OSI Approved :: GNU General Public License (GPL)
Classifier: Operating System :: OS Independent
License-File: LICENSE
